flask_charts/__init__.py
flask_charts/utils.py
flask_charts/static/init_charts.js
flask_charts/templates/chart.html
Flask_Charts-0.1.0.dist-info/LICENSE
Flask_Charts-0.1.0.dist-info/METADATA
Flask_Charts-0.1.0.dist-info/WHEEL
Flask_Charts-0.1.0.dist-info/top_level.txt
Flask_Charts-0.1.0.dist-info/RECORD
